boxing_gym/MTPOPreprocessing.py
boxing_gym/ObsPreprocessing.py
boxing_gym/__init__.py
boxing_gym/data.bin
boxing_gym/mtpo_env.py
boxing_gym-0.1.15.dist-info/LICENSE.txt
boxing_gym-0.1.15.dist-info/METADATA
boxing_gym-0.1.15.dist-info/WHEEL
boxing_gym-0.1.15.dist-info/top_level.txt
boxing_gym-0.1.15.dist-info/RECORD
